{
  "id": "1366c166-b9b5-4bf9-8cf4-c7e8996c6c80",
  "prevId": "3d4cf719-2bca-4033-ad66-c8b8b57d614a",
  "version": "7",
  "dialect": "postgresql",
  "tables": {
    "public.users": {
      "name": "users",
      "schema": "",
      "columns": {
        "id": {
          "name": "id",
          "type": "uuid",
          "primaryKey": true,
          "notNull": true,
          "default": "gen_random_uuid()"
        },
        "name": {
          "name": "name",
          "type": "varchar(15)",
          "primaryKey": false,
          "notNull": true
        },
        "surname": {
          "name": "surname",
          "type": "varchar(20)",
          "primaryKey": false,
          "notNull": true
        },
        "email": {
          "name": "email",
          "type": "varchar(30)",
          "primaryKey": false,
          "notNull": true
        },
        "password": {
          "name": "password",
          "type": "varchar(65)",
          "primaryKey": false,
          "notNull": true
        },
        "isAdmin": {
          "name": "isAdmin",
          "type": "boolean",
          "primaryKey": false,
          "notNull": false,
          "default": false
        },
        "createdAt": {
          "name": "createdAt",
          "type": "timestamp",
          "primaryKey": false,
          "notNull": true,
          "default": "now()"
        },
        "updatedAt": {
          "name": "updatedAt",
          "type": "timestamp",
          "primaryKey": false,
          "notNull": false
        },
        "deletedAt": {
          "name": "deletedAt",
          "type": "timestamp",
          "primaryKey": false,
          "notNull": false
        },
        "isActive": {
          "name": "isActive",
          "type": "boolean",
          "primaryKey": false,
          "notNull": true,
          "default": false
        },
        "avatar": {
          "name": "avatar",
          "type": "varchar(100)",
          "primaryKey": false,
          "notNull": false
        },
        "dateOfBirth": {
          "name": "dateOfBirth",
          "type": "date",
          "primaryKey": false,
          "notNull": true
        }
      },
      "indexes": {},
      "foreignKeys": {},
      "compositePrimaryKeys": {},
      "uniqueConstraints": {
        "users_email_unique": {
          "name": "users_email_unique",
          "nullsNotDistinct": false,
          "columns": [
            "email"
          ]
        }
      },
      "policies": {},
      "checkConstraints": {},
      "isRLSEnabled": false
    },
    "public.blogs": {
      "name": "blogs",
      "schema": "",
      "columns": {
        "id": {
          "name": "id",
          "type": "uuid",
          "primaryKey": true,
          "notNull": true,
          "default": "gen_random_uuid()"
        },
        "userId": {
          "name": "userId",
          "type": "uuid",
          "primaryKey": false,
          "notNull": true
        },
        "title": {
          "name": "title",
          "type": "varchar(30)",
          "primaryKey": false,
          "notNull": true
        },
        "description": {
          "name": "description",
          "type": "varchar(300)",
          "primaryKey": false,
          "notNull": true
        },
        "createdAt": {
          "name": "createdAt",
          "type": "timestamp",
          "primaryKey": false,
          "notNull": true,
          "default": "now()"
        },
        "updatedAt": {
          "name": "updatedAt",
          "type": "timestamp",
          "primaryKey": false,
          "notNull": false
        },
        "isActive": {
          "name": "isActive",
          "type": "boolean",
          "primaryKey": false,
          "notNull": true,
          "default": false
        }
      },
      "indexes": {},
      "foreignKeys": {
        "blogs_userId_users_id_fk": {
          "name": "blogs_userId_users_id_fk",
          "tableFrom": "blogs",
          "tableTo": "users",
          "columnsFrom": [
            "userId"
          ],
          "columnsTo": [
            "id"
          ],
          "onDelete": "no action",
          "onUpdate": "no action"
        }
      },
      "compositePrimaryKeys": {},
      "uniqueConstraints": {},
      "policies": {},
      "checkConstraints": {},
      "isRLSEnabled": false
    },
    "public.comments": {
      "name": "comments",
      "schema": "",
      "columns": {
        "id": {
          "name": "id",
          "type": "uuid",
          "primaryKey": true,
          "notNull": true,
          "default": "gen_random_uuid()"
        },
        "userId": {
          "name": "userId",
          "type": "uuid",
          "primaryKey": false,
          "notNull": false
        },
        "blogId": {
          "name": "blogId",
          "type": "uuid",
          "primaryKey": false,
          "notNull": false
        },
        "content": {
          "name": "content",
          "type": "varchar(100)",
          "primaryKey": false,
          "notNull": true
        },
        "commentedAt": {
          "name": "commentedAt",
          "type": "timestamp",
          "primaryKey": false,
          "notNull": true,
          "default": "now()"
        }
      },
      "indexes": {},
      "foreignKeys": {
        "comments_userId_users_id_fk": {
          "name": "comments_userId_users_id_fk",
          "tableFrom": "comments",
          "tableTo": "users",
          "columnsFrom": [
            "userId"
          ],
          "columnsTo": [
            "id"
          ],
          "onDelete": "no action",
          "onUpdate": "no action"
        },
        "comments_blogId_blogs_id_fk": {
          "name": "comments_blogId_blogs_id_fk",
          "tableFrom": "comments",
          "tableTo": "blogs",
          "columnsFrom": [
            "blogId"
          ],
          "columnsTo": [
            "id"
          ],
          "onDelete": "no action",
          "onUpdate": "no action"
        }
      },
      "compositePrimaryKeys": {},
      "uniqueConstraints": {},
      "policies": {},
      "checkConstraints": {},
      "isRLSEnabled": false
    },
    "public.interactions": {
      "name": "interactions",
      "schema": "",
      "columns": {
        "id": {
          "name": "id",
          "type": "uuid",
          "primaryKey": true,
          "notNull": true,
          "default": "gen_random_uuid()"
        },
        "userId": {
          "name": "userId",
          "type": "uuid",
          "primaryKey": false,
          "notNull": false
        },
        "blogId": {
          "name": "blogId",
          "type": "uuid",
          "primaryKey": false,
          "notNull": false
        },
        "like": {
          "name": "like",
          "type": "boolean",
          "primaryKey": false,
          "notNull": true,
          "default": false
        },
        "dislike": {
          "name": "dislike",
          "type": "boolean",
          "primaryKey": false,
          "notNull": true,
          "default": false
        },
        "interactionAt": {
          "name": "interactionAt",
          "type": "timestamp",
          "primaryKey": false,
          "notNull": true,
          "default": "now()"
        }
      },
      "indexes": {},
      "foreignKeys": {
        "interactions_userId_users_id_fk": {
          "name": "interactions_userId_users_id_fk",
          "tableFrom": "interactions",
          "tableTo": "users",
          "columnsFrom": [
            "userId"
          ],
          "columnsTo": [
            "id"
          ],
          "onDelete": "no action",
          "onUpdate": "no action"
        },
        "interactions_blogId_blogs_id_fk": {
          "name": "interactions_blogId_blogs_id_fk",
          "tableFrom": "interactions",
          "tableTo": "blogs",
          "columnsFrom": [
            "blogId"
          ],
          "columnsTo": [
            "id"
          ],
          "onDelete": "no action",
          "onUpdate": "no action"
        }
      },
      "compositePrimaryKeys": {},
      "uniqueConstraints": {},
      "policies": {},
      "checkConstraints": {},
      "isRLSEnabled": false
    }
  },
  "enums": {},
  "schemas": {},
  "sequences": {},
  "roles": {},
  "policies": {},
  "views": {},
  "_meta": {
    "columns": {},
    "schemas": {},
    "tables": {}
  }
}